<?xml version="1.0" encoding="utf-8" standalone="yes"?>
<Root>
  <PlayField NumLines="8">
    <Line ID="10">
      <Start X="191.5146" Y="6.020014" Z="202.4388" />
      <End X="191.5712" Y="6.017644" Z="205.5609" />
    </Line>
    <Line ID="3">
      <Start X="154.5878" Y="1.020062" Z="196.3654" />
      <End X="154.6093" Y="1.021756" Z="198.2488" />
    </Line>
    <Line ID="9">
      <Start X="218.493" Y="6.019788" Z="205.8442" />
      <End X="218.5202" Y="6.017544" Z="202.3362" />
    </Line>
    <Line ID="4">
      <Start X="257.2162" Y="1.019993" Z="197.1817" />
      <End X="257.2155" Y="1.018168" Z="194.9226" />
    </Line>
    <Line ID="11">
      <Start X="218.5011" Y="6.019788" Z="205.8413" />
      <End X="218.5282" Y="6.017543" Z="202.3333" />
    </Line>
    <Line ID="12">
      <Start X="191.5146" Y="6.020015" Z="202.4388" />
      <End X="191.5712" Y="6.017645" Z="205.5609" />
    </Line>
    <Line ID="14">
      <Start X="154.5878" Y="1.020064" Z="196.3654" />
      <End X="154.6093" Y="1.021758" Z="198.2488" />
    </Line>
    <Line ID="15">
      <Start X="257.2162" Y="1.019994" Z="197.1817" />
      <End X="257.2155" Y="1.018169" Z="194.9226" />
    </Line>
  </PlayField>
</Root>